gapiupdated-1.0.1.data/scripts/gnip_search.py
gapiupdated-1.0.1.data/scripts/gnip_time_series.py
gapiupdated-1.0.1.dist-info/DESCRIPTION.rst
gapiupdated-1.0.1.dist-info/METADATA
gapiupdated-1.0.1.dist-info/RECORD
gapiupdated-1.0.1.dist-info/WHEEL
gapiupdated-1.0.1.dist-info/metadata.json
gapiupdated-1.0.1.dist-info/top_level.txt
search/__init__.py
search/api.py
search/results.py
search/test_api.py
search/test_results.py
